pyplayht/__init__.py
pyplayht/classes.py
pyplayht/types.py
pyplayht-0.1.0.dist-info/LICENSE
pyplayht-0.1.0.dist-info/METADATA
pyplayht-0.1.0.dist-info/WHEEL
pyplayht-0.1.0.dist-info/top_level.txt
pyplayht-0.1.0.dist-info/RECORD
