Metadata-Version: 2.1
Name: pyplayht
Version: 0.1.0
Summary: Python wrapper for PlayHT REST API
Author-email: dobizz <ronnie.code@outlook.com>
License: Apache License
Project-URL: Repository, https://github.com/dobizz/pyplayht
Requires-Python: >=3.8
License-File: LICENSE
Requires-Dist: python-dotenv >=0.20.0
Requires-Dist: requests >=2.28.2
Requires-Dist: retry2 >=0.9.5
